wiz2/__init__.py
wiz2/main.py
wiz2-0.1.7.dist-info/METADATA
wiz2-0.1.7.dist-info/WHEEL
wiz2-0.1.7.dist-info/entry_points.txt
wiz2-0.1.7.dist-info/RECORD
