Metadata-Version: 2.1
Name: wiz2
Version: 0.1.7
Summary: wizmodel.com wiz sdk
Author: incoming
Author-email: 18320122+incomingflyingbrick@users.noreply.github.com
Requires-Python: >=3.9,<4.0
Classifier: Programming Language :: Python :: 3
Classifier: Programming Language :: Python :: 3.9
Classifier: Programming Language :: Python :: 3.10
Classifier: Programming Language :: Python :: 3.11
Requires-Dist: requests (>=2.31.0,<3.0.0)
Requires-Dist: typer[all] (>=0.9.0,<0.10.0)
